lanrzip_utils_components/2630a3e3eab21c607e21.svg
lanrzip_utils_components/295183786cd8a1389865.woff
lanrzip_utils_components/Carousel.py
lanrzip_utils_components/Editor.py
lanrzip_utils_components/LanrzipAiEditor.py
lanrzip_utils_components/LanrzipMermaid.py
lanrzip_utils_components/LanrzipSelectPopup.py
lanrzip_utils_components/LanrzipSlick.py
lanrzip_utils_components/LanrzipUtilsComponents.py
lanrzip_utils_components/__init__.py
lanrzip_utils_components/_imports_.py
lanrzip_utils_components/a4e97f5a2a64f0ab1323.eot
lanrzip_utils_components/async-Editor.js
lanrzip_utils_components/async-Editor.js.map
lanrzip_utils_components/async-LanrzipMermaid.js
lanrzip_utils_components/async-LanrzipMermaid.js.map
lanrzip_utils_components/async-LanrzipUtilsComponents.js
lanrzip_utils_components/async-LanrzipUtilsComponents.js.map
lanrzip_utils_components/async-null.js
lanrzip_utils_components/async-null.js.LICENSE.txt
lanrzip_utils_components/async-null.js.map
lanrzip_utils_components/c94f7671dcc99dce43e2.ttf
lanrzip_utils_components/fb6f3c230cb846e25247.gif
lanrzip_utils_components/lanrzip_utils_components.min.js
lanrzip_utils_components/lanrzip_utils_components.min.js.LICENSE.txt
lanrzip_utils_components/lanrzip_utils_components.min.js.map
lanrzip_utils_components/metadata.json
lanrzip_utils_components/package-info.json
lanrzip_utils_components-0.0.6.dist-info/LICENSE
lanrzip_utils_components-0.0.6.dist-info/METADATA
lanrzip_utils_components-0.0.6.dist-info/WHEEL
lanrzip_utils_components-0.0.6.dist-info/top_level.txt
lanrzip_utils_components-0.0.6.dist-info/RECORD
