Metadata-Version: 2.1
Name: lanrzip-utils-components
Version: 0.0.6
Summary: Project Description
Home-page: UNKNOWN
Author: Lanrzip <lanrzip@163.com>
License: MIT
Platform: UNKNOWN
Classifier: Framework :: Dash
Requires-Dist: dash ==2.11.0
